MANIFEST.in
setup.py
dbconfig/__init__.py
dbconfig/admin.py
dbconfig/models.py
dbconfig/utils.py
dbconfig.egg-info/PKG-INFO
dbconfig.egg-info/SOURCES.txt
dbconfig.egg-info/dependency_links.txt
dbconfig.egg-info/not-zip-safe
dbconfig.egg-info/requires.txt
dbconfig.egg-info/top_level.txt
dbconfig/templates/admin/dbconfig_list.html