Metadata-Version: 1.0
Name: dbconfig
Version: 0.1.5
Summary: store config in database
Home-page: UNKNOWN
Author: Viktor Kotseruba
Author-email: barbuzaster@gmail.com
License: MIT
Keywords: config web django
Platform: UNKNOWN
